<DOMSymbolItem xmlns:xsi="http://www.w3.org/2001/XMLSchema-instance" xmlns="http://ns.adobe.com/xfl/2008/" name="Duplicate Items Folder/Symbol 414 copy 3" itemID="619336b1-000014ba" symbolType="graphic" lastModified="1637037779">
  <timeline>
    <DOMTimeline name="Symbol 414 copy 3" layerDepthEnabled="true">
      <layers>
        <DOMLayer name="Layer_1" color="#00FFFF" current="true" isSelected="true">
          <frames>
            <DOMFrame index="0" keyMode="9728">
              <elements>
                <DOMShape>
                  <fills>
                    <FillStyle index="1">
                      <SolidColor/>
                    </FillStyle>
                    <FillStyle index="2">
                      <SolidColor color="#A7A3BE"/>
                    </FillStyle>
                    <FillStyle index="3">
                      <SolidColor color="#5C586C"/>
                    </FillStyle>
                    <FillStyle index="4">
                      <SolidColor color="#4B4859"/>
                    </FillStyle>
                    <FillStyle index="5">
                      <SolidColor color="#FFFFFF"/>
                    </FillStyle>
                  </fills>
                  <edges>
                    <Edge fillStyle1="1" edges="!-60 224[-138 226 -176 218!-176 218[-191 216 -194 209!-194 209[-198 202 -194 187!-194 187[-140 1 -64 -165!-64 -165[-57 -183 -48 -193!-48 -193[-42 -202 -31 -207!-31 -207[-11 -219 22 -218!22 -218[41 -217 79 -214!79 -214[101 -214 109 -208
!109 -208[115 -204 121 -190!121 -190[140 -147 167 -48!167 -48|231 196!231 196[235 205 232 213!232 213[228 223 205 223!205 223[64 220 -60 224"/>
                    <Edge fillStyle0="2" fillStyle1="5" edges="
!121 -0.5|121.5 -0.5!121.5 -0.5[#61.17 #FFFFA5.19 65 -167!65 -167|6 -157!6 -157[-2 -157 -6 -153!-6 -153[-10 -151 -14 -143!-14 -143|-68 -14!-68 -14[#FFFFB9.7E #FFFFF8.FF -72.5 -1!-72.5 -1[-68.890625 #FFFFFE.D9 -65.5 -1.5"/>
                    <Edge fillStyle0="5" fillStyle1="1" edges="
!156 25|151 6.5!151 6.5[#96.3A #3.C1 149.5 1!149.5 1|142 -27!142 -27[126 -87 116 -116!116 -116|91 -181!91 -181[40 -189 -12 -181!-12 -181[-22 -179 -25 -176!-25 -176[-30 -172 -32 -166!-32 -166[#FFFFC2.3E #FFFF99.53 -88 -36"/>
                    <Edge fillStyle0="2" fillStyle1="4" edges="
!-65.5 -1.5[#1B.E8 #FFFFFB.15 121 -0.5"/>
                    <Edge fillStyle0="5" fillStyle1="4" edges="
!159.5 39[#9E.C2 #26.F1 158 39!158 39|156 26.5!156 26.5|156 25"/>
                    <Edge fillStyle0="4" fillStyle1="1" edges="
!159.5 39|156 25"/>
                    <Edge fillStyle0="5" fillStyle1="3" edges="
!128 37[#88.E4 #25.7B 145.5 38!145.5 38[#8B.55 #25.C2 133 37.5!133 37.5[#89.5D #31.01 141 69!141 69[149 114 164 164!164 164[#A7.A3 #B0.BB 171.5 188.5"/>
                    <Edge fillStyle0="4" fillStyle1="5" edges="
!128 37[#7D.F1 #1A.A8 124 15!124 15|121 -0.5"/>
                    <Edge fillStyle0="5" fillStyle1="1" edges="
!171.5 188.5|197 188!197 188[196 177 186 138!186 138|159.5 39"/>
                    <Edge fillStyle0="2" fillStyle1="5" edges="
!-101 0.5[#FFFF9B.C2 #0.75 -99.5 0.5!-99.5 0.5[#FFFFA1.8A #FFFFEF.61 -88 -36"/>
                    <Edge fillStyle0="3" fillStyle1="5" edges="
!-81.5 47|-82.5 47!-82.5 47|-113 138!-113 138[#FFFF84.F2 #A7.68 -131.5 192"/>
                    <Edge fillStyle0="4" fillStyle1="5" edges="
!-65.5 -1.5[#FFFFBA.46 #B.2 -75 28!-75 28[-78.703125 #26.D4 -81.5 47"/>
                    <Edge fillStyle0="3" fillStyle1="4" edges="
!128 37[#3F.38 #22.37 -12 40!-12 40[#FFFFDA.1B #29.C1 -81.5 47"/>
                    <Edge fillStyle0="4" fillStyle1="1" edges="
!-102 0.5|-102 1!-102 1[-102.90625 #2.FA -103.5 5!-103.5 5[#FFFF92.9E #14.F1 -115 37!-115 37[#FFFF8A.74 #2C.39 -120 51.5"/>
                    <Edge fillStyle0="3" fillStyle1="4" edges="
!-118.5 51[#FFFF88.C5 #33.64 -120 51.5"/>
                    <Edge fillStyle0="5" fillStyle1="4" edges="
!-101 0.5[#FFFF92.C6 #17.DA -118 51!-118 51|-118.5 51"/>
                    <Edge fillStyle0="3" fillStyle1="5" edges="
!-159.5 189.5[#FFFF6B.A4 #89.06 -132 89!-132 89|-118.5 51"/>
                    <Edge fillStyle0="3" fillStyle1="1" edges="
!-120 51.5[-140.875 #6F.C -159 174.5!-159 174.5[#FFFF5F.0E #B5.AB -163 189!-163 189[#FFFF5E.A5 #BD.46 -159.5 189.5"/>
                    <Edge fillStyle0="5" fillStyle1="1" edges="
!-159.5 189.5|-158.5 189.5!-158.5 189.5[#FFFF65.57 #BE.12 -150 190.5!-150 190.5[#FFFF72.0D #BF.66 -131.5 192"/>
                    <Edge fillStyle0="3" fillStyle1="1" edges="
!-131.5 192[-107.59375 193 -71 193!-71 193|171.5 188.5"/>
                    <Edge fillStyle0="2" fillStyle1="4" edges="
!-102 0.5|-101 0.5"/>
                    <Edge fillStyle0="2" fillStyle1="1" edges="
!-88 -36[#FFFFA0.DF #FFFFEE.21 -102 0.5"/>
                    <Edge cubics="!-60 224(;-99,225 -138,226 -176,218q-60 224Q-138 226q-176 218);"/>
                    <Edge cubics="!-176 218(;-183,217 -191,215 -194,209q-176 218Q-191 216q-194 209);"/>
                    <Edge cubics="!-194 209(;-198,203 -196,194 -194,187q-194 209Q-198 202q-194 187);"/>
                    <Edge cubics="!-194 187(;-159,67 -116,-51 -64,-165q-194 187Q-140 1q-64 -165);"/>
                    <Edge cubics="!-64 -165(;-60,-175 -55,-185 -48,-193q-64 -165Q-57 -183q-48 -193);"/>
                    <Edge cubics="!-48 -193(;-44,-199 -38,-204 -31,-207q-48 -193Q-42 -202q-31 -207);"/>
                    <Edge cubics="!-31 -207(;1,-226 41,-214 79,-214q-31 -207Q-11 -219q22 -218Q41 -217q79 -214);"/>
                    <Edge cubics="!79 -214(;89,-214 101,-214 109,-208q79 -214Q101 -214q109 -208);"/>
                    <Edge cubics="!109 -208(;115,-204 118,-197 121,-190q109 -208Q115 -204q121 -190);"/>
                    <Edge cubics="!121 -190(;141,-145 154,-96 167,-48q121 -190Q140 -147q167 -48);"/>
                    <Edge cubics="!167 -48(;188,33 210,114 231,196q167 -48 231 196);"/>
                    <Edge cubics="!231 196(;233,201 234,207 232,213q231 196Q235 205q232 213);"/>
                    <Edge cubics="!232 213(;228,222 215,223 205,223q232 213Q228 223q205 223);"/>
                    <Edge cubics="!205 223(;117,221 28,221 -60,224q205 223Q64 220q-60 224);"/>
                    <Edge cubics="!197 188(;195,171 190,154 186,138q197 188Q196 177q186 138);"/>
                    <Edge cubics="!142 -27(;134,-57 126,-87 116,-116q142 -27Q126 -87q116 -116);"/>
                    <Edge cubics="!116 -116(;108,-138 100,-160 91,-181q116 -116 91 -181);"/>
                    <Edge cubics="!91 -181(;57,-186 22,-186 -12,-181q91 -181Q40 -189q-12 -181);"/>
                    <Edge cubics="!-12 -181(;-17,-180 -22,-179 -25,-176q-12 -181Q-22 -179q-25 -176);"/>
                    <Edge cubics="!-25 -176(;-29,-173 -31,-169 -32,-166q-25 -176Q-30 -172q-32 -166);"/>
                    <Edge cubics="!150 1(;150,1 142,-27 142,-27q150 1 142 -27);"/>
                    <Edge cubics="!-102 1(;-103,2 -103,4 -103,5q-102 1Q-103 3q-103 5);"/>
                    <Edge cubics="!-103 5(;-107,16 -111,26 -115,37q-103 5Q-109 21q-115 37);"/>
                    <Edge cubics="!-115 37(;-117,42 -119,47 -120,52q-115 37Q-118 44q-120 52);"/>
                    <Edge cubics="!-159 175(;-160,180 -162,184 -163,189q-159 175Q-161 182q-163 189);"/>
                    <Edge cubics="!-120 52(;-134,92 -147,133 -159,175q-120 52Q-141 112q-159 175);"/>
                    <Edge cubics="!186 138(;186,138 160,39 160,39q186 138 160 39);"/>
                    <Edge cubics="!65 -167(;45,-164 25,-161 6,-157q65 -167 6 -157);"/>
                    <Edge cubics="!6 -157(;2,-157 -3,-156 -6,-153q6 -157Q-2 -157q-6 -153);"/>
                    <Edge cubics="!-6 -153(;-10,-151 -12,-147 -14,-143q-6 -153Q-10 -151q-14 -143);"/>
                    <Edge cubics="!122 0(;105,-61 86,-116 65,-167q122 0Q97 -91q65 -167);"/>
                    <Edge cubics="!-32 -166(;-52,-124 -71,-81 -88,-36q-32 -166Q-62 -103q-88 -36);"/>
                    <Edge cubics="!-14 -143(;-14,-143 -68,-14 -68,-14q-14 -143 -68 -14);"/>
                    <Edge cubics="!-68 -14(;-70,-9 -71,-5 -72,-1q-68 -14Q-71 -7q-72 -1);"/>
                    <Edge cubics="!-99 1(;-96,-11 -92,-23 -88,-36q-99 1Q-94 -17q-88 -36);"/>
                    <Edge cubics="!-88 -36(;-93,-24 -97,-12 -102,1q-88 -36Q-95 -18q-102 1);"/>
                    <Edge cubics="!-65 -1(;-68,-1 -70,-1 -72,-1q-65 -1Q-69 -1q-72 -1);"/>
                    <Edge cubics="!-101 1(;-100,0 -100,0 -99,1q-101 1Q-100 0q-99 1);"/>
                    <Edge cubics="!-75 28(;-78,35 -80,42 -81,47q-75 28Q-79 39q-81 47);"/>
                    <Edge cubics="!-12 40(;-29,41 -52,44 -81,47q-12 40Q-38 42q-81 47);"/>
                    <Edge cubics="!-118 51(;-119,51 -119,51 -120,52q-118 51Q-119 51q-120 52);"/>
                    <Edge cubics="!-118 51(;-112,33 -106,16 -101,1q-118 51Q-109 24q-101 1);"/>
                    <Edge cubics="!-102 1(;-102,1 -101,1 -101,1q-102 1 -101 1);"/>
                    <Edge cubics="!-65 -1(;-68,7 -72,17 -75,28q-65 -1Q-70 11q-75 28);"/>
                    <Edge cubics="!-81 47(;-81,47 -82,47 -82,47q-81 47 -82 47);"/>
                    <Edge cubics="!-132 89(;-132,89 -118,51 -118,51q-132 89 -118 51);"/>
                    <Edge cubics="!-113 138(;-120,157 -126,175 -131,192q-113 138Q-123 167q-131 192);"/>
                    <Edge cubics="!-159 190(;-159,190 -158,190 -158,190q-159 190 -158 190);"/>
                    <Edge cubics="!-163 189(;-162,189 -160,189 -159,190q-163 189Q-161 189q-159 190);"/>
                    <Edge cubics="!-82 47(;-82,47 -113,138 -113,138q-82 47 -113 138);"/>
                    <Edge cubics="!-159 190(;-152,155 -143,121 -132,89q-159 190Q-148 137q-132 89);"/>
                    <Edge cubics="!-131 192(;-116,193 -96,193 -71,193q-131 192Q-108 193q-71 193);"/>
                    <Edge cubics="!-158 190(;-156,190 -153,190 -150,191q-158 190Q-155 190q-150 191);"/>
                    <Edge cubics="!-150 191(;-145,191 -138,191 -131,192q-150 191Q-142 191q-131 192);"/>
                    <Edge cubics="!122 0(;122,0 121,0 121,0q122 0 121 0);"/>
                    <Edge cubics="!160 39(;159,39 159,39 158,39q160 39Q159 39q158 39);"/>
                    <Edge cubics="!160 39(;160,39 156,25 156,25q160 39 156 25);"/>
                    <Edge cubics="!156 25(;156,25 156,27 156,27q156 25 156 27);"/>
                    <Edge cubics="!156 27(;156,27 158,39 158,39q156 27 158 39);"/>
                    <Edge cubics="!128 37(;127,30 125,23 124,15q128 37Q126 27q124 15);"/>
                    <Edge cubics="!124 15(;124,15 121,0 121,0q124 15 121 0);"/>
                    <Edge cubics="!-65 -1(;-3,-4 59,-3 121,0q-65 -1Q28 -5q121 0);"/>
                    <Edge cubics="!128 37(;85,35 38,36 -12,40q128 37Q63 34q-12 40);"/>
                    <Edge cubics="!164 164(;155,133 147,101 141,69q164 164Q149 114q141 69);"/>
                    <Edge cubics="!151 7(;150,5 150,3 150,1q151 7Q150 4q150 1);"/>
                    <Edge cubics="!156 25(;156,25 151,7 151,7q156 25 151 7);"/>
                    <Edge cubics="!146 38(;140,37 134,37 128,37q146 38Q137 37q128 37);"/>
                    <Edge cubics="!146 38(;141,38 137,38 133,38q146 38Q139 38q133 38);"/>
                    <Edge cubics="!158 39(;158,39 146,38 146,38q158 39 146 38);"/>
                    <Edge cubics="!141 69(;138,56 136,45 133,38q141 69Q137 49q133 38);"/>
                    <Edge cubics="!172 189(;169,181 167,173 164,164q172 189Q168 177q164 164);"/>
                    <Edge cubics="!172 189(;172,189 197,188 197,188q172 189 197 188);"/>
                    <Edge cubics="!-71 193(;-71,193 172,189 172,189q-71 193 172 189);"/>
                  </edges>
                </DOMShape>
              </elements>
            </DOMFrame>
          </frames>
        </DOMLayer>
      </layers>
    </DOMTimeline>
  </timeline>
</DOMSymbolItem>