<DOMSymbolItem xmlns:xsi="http://www.w3.org/2001/XMLSchema-instance" xmlns="http://ns.adobe.com/xfl/2008/" name="game/Symbol 474" itemID="61931412-00000382" symbolType="graphic" lastModified="1637028882">
  <timeline>
    <DOMTimeline name="Symbol 474" layerDepthEnabled="true">
      <layers>
        <DOMLayer name="Layer_1" color="#00FFFF" current="true" isSelected="true">
          <frames>
            <DOMFrame index="0" keyMode="9728">
              <elements>
                <DOMShape>
                  <fills>
                    <FillStyle index="1">
                      <SolidColor/>
                    </FillStyle>
                  </fills>
                  <edges>
                    <Edge fillStyle1="1" edges="!13 96S2|50 46!50 46|86 12!86 12[95 1 100 0!100 0[108 -1 117 6!117 6[149 30 172 59!172 59[198 89 206 117!206 117[210 126 206 131!206 131[203 138 186 140!186 140|51 136!51 136[14 136 0 129!0 129[-2 119 7 106!7 106|13 96"/>
                    <Edge cubics="!86 12(;90,7 94,1 100,0q86 12Q95 1q100 0);"/>
                    <Edge cubics="!100 0(;106,-1 112,2 117,6q100 0Q108 -1q117 6);"/>
                    <Edge cubics="!117 6(;137,21 156,39 172,59q117 6Q149 30q172 59);"/>
                    <Edge cubics="!172 59(;187,76 200,95 206,117q172 59Q198 89q206 117);"/>
                    <Edge cubics="!206 117(;208,122 209,127 206,131q206 117Q210 126q206 131);"/>
                    <Edge cubics="!206 131(;203,138 194,139 186,140q206 131Q203 138q186 140);"/>
                    <Edge cubics="!51 136(;34,136 16,137 0,129q51 136Q14 136q0 129);"/>
                    <Edge cubics="!0 129(;-2,121 2,113 7,106q0 129Q-2 119q7 106);"/>
                    <Edge cubics="!7 106(;9,103 11,99 13,96q7 106 13 96);"/>
                    <Edge cubics="!50 46(;50,46 86,12 86,12q50 46 86 12);"/>
                    <Edge cubics="!186 140(;186,140 51,136 51,136q186 140 51 136);"/>
                    <Edge cubics="!13 96(;13,96 50,46 50,46q13 96 50 46);"/>
                  </edges>
                </DOMShape>
              </elements>
            </DOMFrame>
          </frames>
        </DOMLayer>
      </layers>
    </DOMTimeline>
  </timeline>
</DOMSymbolItem>